main1.v
module ALU1 #(parameter INPUT = 8)(input  wire [INPUT-1:0]  OPA,
    input  wire [INPUT-1:0]  OPB,
    input  wire              CIN,
    input  wire              CLK,
    input  wire              RST,
    input  wire [3:0]        CMD,
    input  wire              CE,
    input  wire              MODE,
    input  wire [1:0]        VALID,

    output reg               ERR,
    output reg [(INPUT*2)-1:0]  RES,
    output reg               OFLOW,
    output reg               COUT,
    output reg               G,
    output reg               L,
    output reg               E
);

reg signed [INPUT-1:0] signed_reg_OPA;
reg signed [INPUT-1:0] signed_reg_OPB;

//input temp reg 
reg [INPUT-1:0] temp_OPA;
reg [INPUT-1:0] temp_OPB;
reg temp_CIN;
reg [3:0] temp_CMD;
reg temp_MODE;
reg [1:0] temp_VALID;
reg [(INPUT*2)-1:0] buff1;  //buff for mul

always @(posedge CLK or posedge RST)begin 
	if(RST)begin 
		RES <= 16'b0;
		ERR <= 1'b0;
		OFLOW <= 1'b0;
		COUT <= 1'b0;
		G <= 1'b0;
		L <= 1'b0;
		E <= 1'b0;
		signed_reg_OPA <= 'd0;
		signed_reg_OPB <= 'd0;
		temp_OPA <= 'd0;
		temp_OPB <= 'd0;
		temp_CIN <= 'd0;
		temp_CMD <= 'd0;
		temp_MODE <= 'd0;
		temp_VALID <= 'd0;
		buff1 <= 'd0;
	end
	else begin 
		temp_OPA <= OPA;
		temp_OPB <= OPB;
		temp_CIN <= CIN;
		temp_CMD <= CMD;
		temp_MODE <= MODE;
		temp_VALID <= VALID;
		signed_reg_OPA <= OPA;
		signed_reg_OPB <= OPB;
	end
end

always @(posedge CLK)begin 
	if(CE)begin 
		if(temp_MODE == 1)begin
                	RES <= 0;
			ERR <= 1'b0;
			OFLOW <= 1'b0;
                	G <= 1'b0;
                	L <= 1'b0;
               		E <= 1'b0;	
			case(temp_VALID)
				2'b11:begin 
					case(temp_CMD)
					 4'b0000:begin
                               			 RES[(INPUT):0] <= temp_OPA + temp_OPB;
						end
					4'b0001:begin 
						 RES[(INPUT):0] <= temp_OPA - temp_OPB;
                               			 OFLOW <= (temp_OPA<temp_OPB) ? 1:0;
						end
					4'b0010:begin 
						RES[(INPUT):0] <= temp_OPA + temp_OPB + temp_CIN;
						end
					4'b0011:begin 
						 RES[(INPUT):0] <= temp_OPA - temp_OPB - temp_CIN;
                               			 OFLOW <= ((temp_OPA < temp_OPB) || ((temp_OPA == temp_OPB)&&(temp_CIN == 1))) ? 1: 0;
						end
					4'b1000:begin 
						if(temp_OPA == temp_OPB)begin
                                       		E <= 1;
                                       		G <= 0;
                                        	L <= 0;
                               		 end
                               			else if(temp_OPA > temp_OPB)begin
                                        	E <= 0;
                                        	G <= 1;
                                        	L <= 0;
                                	end
                                		else begin
                                       		 E <= 0;
                                        	 G <= 0;
                                        	 L <= 1;

                                	end
                       		 end
					4'b1001:begin 
						buff1 <= ((temp_OPA+1) * (temp_OPB+1));
						RES <= buff1;
                        			end
					4'b1010:begin 
						 buff1 <= ((temp_OPA << 1)*temp_OPB);
						 RES <= buff1;
                        			end
					4'b1011:begin 
						RES[INPUT-1:0] <= signed_reg_OPA + signed_reg_OPB;
                               			 if(signed_reg_OPA == signed_reg_OPB)begin
                                       		 E <= 1;
                                       		 G <= 0;
                                       		 L <= 0;
                               		 end
                                		else if(signed_reg_OPA > signed_reg_OPB)begin
                                        E <= 0;
                                        G <= 1;
                                        L <= 0;
                                end
                                else begin
                                        E <= 0;
                                        G <= 0;
                                        L <= 1;

                                end

                        end
				4'b1100:begin
                                RES[INPUT:0] <= signed_reg_OPA - signed_reg_OPB;
                                if(signed_reg_OPA == signed_reg_OPB)begin
                                        E <= 1;
                                        G <= 0;
                                        L <= 0;
                                end
                                else if(signed_reg_OPA > signed_reg_OPB)begin
                                        E <= 0;
                                        G <= 1;
                                        L <= 0;
                                end
                                else begin
                                        E <= 0;
                                        G <= 0;
                                        L <= 1;

                                end

                                end

					default: begin  RES <= 0;OFLOW <=0;ERR<=1;end
				endcase
			end
			2'b01:begin 
				case(temp_CMD)
				4'b0100:begin 
					RES[(INPUT):0] <= temp_OPA+1;
			 end
				4'b0101:begin 
					 RES[(INPUT):0] <= temp_OPA-1;
                                	OFLOW <= (temp_OPA == 0) ? 1:0;
                       		 end
				default: begin RES <= 0;OFLOW <= 0;ERR<=1;end
			endcase 
		end
		2'b10:begin 
			case(temp_CMD)
				4'b0110:begin 
					RES[(INPUT):0] <= temp_OPB+1;
                       		 end
				4'b0111:begin 
					 RES[(INPUT):0] <= temp_OPB - 1;
	                                OFLOW <= (temp_OPB == 0) ? 1:0;
                       			 end
				default:begin RES<=0;OFLOW<=0;ERR<=1;end
			endcase 
		end
		default: begin 
			RES <= 0;ERR <= 1;end
		endcase 

	end
 	else begin 
		RES <= 0;
                ERR <= 1'b0;
                OFLOW <= 1'b0;
                G <= 1'b0;
                L <= 1'b0;
                E <= 1'b0;
	case(temp_VALID)
		2'b11:begin
			 case(temp_CMD)
				4'b0000: RES[INPUT-1:0] <= temp_OPA & temp_OPB;
				4'b0001: RES[INPUT-1:0] <= ~(temp_OPA & temp_OPB);
				4'b0010: RES[INPUT-1:0] <= temp_OPA | temp_OPB;
				4'b0011: RES[INPUT-1:0] <= ~(temp_OPA | temp_OPB);
				4'b0100: RES[INPUT-1:0] <= temp_OPA ^ temp_OPB;
				4'b0101: RES[INPUT-1:0] <= ~(temp_OPA ^ temp_OPB);
				4'b1100:begin
					if(temp_OPB[INPUT-1:($clog2(INPUT)+1)] == 0)
						ERR <= 0;
					else 
						ERR <= 1;
					RES[INPUT-1:0] <= (temp_OPA << temp_OPB[$clog2(INPUT)-1:0]) | (temp_OPA >> (INPUT - temp_OPB[$clog2(INPUT)-1:0])); 
				end
				4'b1101:begin 
					 if(temp_OPB[INPUT-1:($clog2(INPUT)+1)] == 0)
						ERR <= 0;
					else 
						ERR <= 1;
					RES[INPUT-1:0] <= (temp_OPA >> temp_OPB[$clog2(INPUT)-1:0]) | (temp_OPA << (INPUT - temp_OPB[$clog2(INPUT)-1:0])); 
				end
				default :begin RES[INPUT-1:0] <= 0;ERR<=1;end
			endcase 
		end
		2'b01:begin 
			case(temp_CMD)
				4'b0110: RES[INPUT-1:0] <= ~temp_OPA;
				4'b1000: RES[INPUT-1:0] <= temp_OPA >> 1;
				4'b1001: RES[INPUT-1:0] <= temp_OPA << 1;
				default :begin RES[INPUT-1:0] <= 0;ERR<=1;
					end
			endcase
		end
		2'b10:begin 
			case(temp_CMD)
				4'b0111: RES[INPUT-1:0] <= ~temp_OPB;
				4'b1010: RES[INPUT-1:0] <= temp_OPB >> 1;
				4'b1011: RES[INPUT-1:0] <= temp_OPB << 1;
				default :begin RES[INPUT-1:0] <= 0;ERR<=1;
				end
			endcase 
			end
	default: begin RES[INPUT-1:0] <= 0;ERR <=1;end
	endcase 
	end
end
end

always@(RES) begin 
		if(CE)begin 
			COUT = 0; 
			case(temp_CMD)
				 4'b0000:begin 
				 COUT = RES[INPUT];
				 end
            			 4'b0010:begin 
				 COUT = RES[INPUT];
			  	 end
           			 4'b0100:begin 
				 COUT = RES[INPUT];
				 end
           			 4'b0110:begin 
				 COUT = RES[INPUT];
				end
				4'b1011:begin 
				OFLOW = ((~signed_reg_OPA[INPUT-1]&~signed_reg_OPB[INPUT-1]&RES[INPUT-1])|(signed_reg_OPA[INPUT-1]&signed_reg_OPB[INPUT-1]&~RES[INPUT-1]));
				end
				4'b1100:begin
				OFLOW = ((signed_reg_OPA[INPUT-1] != signed_reg_OPB[INPUT-1]) && (RES[INPUT-1] != signed_reg_OPA[INPUT-1]));
				end
				default: begin COUT = 0;end
			endcase
		end
	end
endmodule

demo_mul.v
`timescale 1ns/1ps
module ALU1_tb;
  parameter INPUT = 8;
  
  reg [INPUT-1:0] OPA, OPB;
  reg CIN, CLK, RST, CE, MODE;
  reg [3:0] CMD;
  reg [1:0] VALID;
  wire [(INPUT*2)-1:0] RES;
  wire ERR, OFLOW, COUT, G, L, E;

  ALU1 #(.INPUT(INPUT)) dut (
    .OPA(OPA), .OPB(OPB),
    .CIN(CIN), .CLK(CLK),
    .RST(RST), .CMD(CMD),
    .CE(CE), .MODE(MODE),
    .VALID(VALID),
    .RES(RES), .ERR(ERR),
    .OFLOW(OFLOW), .COUT(COUT),
    .G(G), .L(L), .E(E)
  );

  initial CLK = 0;
  always #5 CLK = ~CLK;  // 10ns clock

  initial begin 
	  $dumpfile("dump.vcd");
	  $dumpvars(0,ALU1_tb);
end



  task reset;
    begin
      RST = 1;
      CE = 0;
      #10;
      RST = 0;
    end
  endtask

  task apply_inputs(input [3:0] cmd_i, input [INPUT-1:0] a, b, input cin_i);
    begin
      @(negedge CLK);
      CMD = cmd_i;
      OPA = a;
      OPB = b;
      CIN = cin_i;
      CE = 1;
      MODE = 1;
      VALID = 2'b11;
    end
  endtask

  initial begin
    $display("Starting ALU Arithmetic Test (neg edge)...");
    reset;
    apply_inputs(4'b1000,8'd3,8'd3,1'b0);
    @(negedge CLK);

    apply_inputs(4'b1000,8'd5,8'd3,1'b0);
    @(negedge CLK);

    apply_inputs(4'b1000,-1'd1,-1'd1,1'b0);
    @(negedge CLK);

    apply_inputs(4'b1000,-3'd5,3'd3,1'b0);
    @(negedge CLK);

    apply_inputs(4'b1000,3'd3,3'd5,1'b0);
    @(negedge CLK);
    @(negedge CLK);

    apply_inputs(4'b1001,3'd3,3'd4,1'b0);
    @(negedge CLK);
    @(negedge CLK);

    apply_inputs(4'b1001,8'd255,8'd255,1'b0);
    @(negedge CLK);
    @(negedge CLK);

    apply_inputs(4'b1001,8'd0,8'd0,1'b0);
    @(negedge CLK);
    @(negedge CLK);

    apply_inputs(4'b1001,-8'd1,-8'd1,1'b0);
    @(negedge CLK);
    @(negedge CLK);

    apply_inputs(4'b1001,8'd254,8'd254,1'b0);
    @(negedge CLK);
    @(negedge CLK);

    apply_inputs(4'b1010,8'd3,8'd4,1'b0);
    @(negedge CLK);
    @(negedge CLK);

    apply_inputs(4'b1010,8'd255,8'd255,1'b0);
    @(negedge CLK);
    @(negedge CLK);
    @(negedge CLK);
	
 
    @(negedge CLK);
    apply_inputs(4'b0000,8'd5,8'd10,1'b0);
    @(negedge CLK);
    @(negedge CLK);
    CE = 0;
    $display("Arithmetic test complete.");
    #20;
    $finish;
	
  end

endmodule

dump.vcd
$date
	Tue May 27 16:31:13 2025
$end
$version
	Icarus Verilog
$end
$timescale
	1ps
$end
$scope module ALU1_tb $end
$var wire 16 ! RES [15:0] $end
$var wire 1 " OFLOW $end
$var wire 1 # L $end
$var wire 1 $ G $end
$var wire 1 % ERR $end
$var wire 1 & E $end
$var wire 1 ' COUT $end
$var parameter 32 ( INPUT $end
$var reg 1 ) CE $end
$var reg 1 * CIN $end
$var reg 1 + CLK $end
$var reg 4 , CMD [3:0] $end
$var reg 1 - MODE $end
$var reg 8 . OPA [7:0] $end
$var reg 8 / OPB [7:0] $end
$var reg 1 0 RST $end
$var reg 2 1 VALID [1:0] $end
$scope module dut $end
$var wire 1 ) CE $end
$var wire 1 * CIN $end
$var wire 1 + CLK $end
$var wire 4 2 CMD [3:0] $end
$var wire 1 - MODE $end
$var wire 8 3 OPA [7:0] $end
$var wire 8 4 OPB [7:0] $end
$var wire 1 0 RST $end
$var wire 2 5 VALID [1:0] $end
$var parameter 32 6 INPUT $end
$var reg 1 ' COUT $end
$var reg 1 & E $end
$var reg 1 % ERR $end
$var reg 1 $ G $end
$var reg 1 # L $end
$var reg 1 " OFLOW $end
$var reg 16 7 RES [15:0] $end
$var reg 16 8 buff1 [15:0] $end
$var reg 8 9 signed_reg_OPA [7:0] $end
$var reg 8 : signed_reg_OPB [7:0] $end
$var reg 1 ; temp_CIN $end
$var reg 4 < temp_CMD [3:0] $end
$var reg 1 = temp_MODE $end
$var reg 8 > temp_OPA [7:0] $end
$var reg 8 ? temp_OPB [7:0] $end
$var reg 2 @ temp_VALID [1:0] $end
$upscope $end
$scope task apply_inputs $end
$var reg 8 A a [7:0] $end
$var reg 8 B b [7:0] $end
$var reg 1 C cin_i $end
$var reg 4 D cmd_i [3:0] $end
$upscope $end
$scope task reset $end
$upscope $end
$upscope $end
$enddefinitions $end
$comment Show the parameter values. $end
$dumpall
b1000 6
b1000 (
$end
#0
$dumpvars
bx D
xC
bx B
bx A
b0 @
b0 ?
b0 >
0=
b0 <
0;
b0 :
b0 9
b0 8
b0 7
bx 5
bx 4
bx 3
bx 2
bx 1
10
bx /
bx .
x-
bx ,
0+
x*
0)
0'
0&
0%
0$
0#
0"
b0 !
$end
#5000
1+
#10000
b11 1
b11 5
1-
1)
0*
b1 /
b1 4
b1111111 .
b1111111 3
b1011 ,
b1011 2
0+
0C
b1 B
b1111111 A
b1011 D
00
#15000
1%
b1 :
b1111111 9
b11 @
1=
b1011 <
b1 ?
b1111111 >
1+
#20000
b10000000 B
b10000000 A
0+
#25000
1"
1$
b10000000 !
b10000000 7
0%
1+
#30000
b10000000 /
b10000000 4
b10000000 .
b10000000 3
0+
#35000
1$
0"
b10000000 !
b10000000 7
b10000000 :
b10000000 9
b10000000 ?
b10000000 >
1+
#40000
b11111111 B
0+
#45000
1"
1&
0$
b0 !
b0 7
1+
#50000
b11111111 /
b11111111 4
0+
#55000
1&
0"
b11111111 :
b11111111 ?
1+
#60000
b111111 B
b1000000 A
0+
#65000
1"
1#
b1111111 !
b1111111 7
0&
1+
#70000
b111111 /
b111111 4
b1000000 .
b1000000 3
0+
#75000
1#
0"
b1111111 !
b1111111 7
b111111 :
b1000000 9
b111111 ?
b1000000 >
1+
#80000
b100110 B
b1011010 A
0+
#85000
1$
0#
b1111111 !
b1111111 7
1+
#90000
b100110 /
b100110 4
b1011010 .
b1011010 3
0+
#95000
1$
b1111111 !
b1111111 7
b100110 :
b1011010 9
b100110 ?
b1011010 >
1+
#100000
b11000001 B
b11000000 A
0+
#105000
1"
1$
b10000000 !
b10000000 7
1+
#110000
b11000001 /
b11000001 4
b11000000 .
b11000000 3
0+
#115000
1$
0"
b10000000 !
b10000000 7
b11000001 :
b11000000 9
b11000001 ?
b11000000 >
1+
#120000
b10100 B
b11001110 A
0+
#125000
1#
0$
b10000001 !
b10000001 7
1+
#130000
b10100 /
b10100 4
b11001110 .
b11001110 3
0+
#135000
1#
b10000001 !
b10000001 7
b10100 :
b11001110 9
b10100 ?
b11001110 >
1+
#140000
0+
#145000
1#
b11100010 !
b11100010 7
1+
#150000
b11111111 B
b1111111 A
b1100 D
0+
#155000
1#
b11100010 !
b11100010 7
1+
#160000
b11111111 /
b11111111 4
b1111111 .
b1111111 3
b1100 ,
b1100 2
0+
#165000
1"
1#
b11100010 !
b11100010 7
b11111111 :
b1111111 9
b1100 <
b11111111 ?
b1111111 >
1+
#170000
b1 B
b10000000 A
0+
#175000
1$
0#
1"
b10000000 !
b10000000 7
1+
#180000
b1 /
b1 4
b10000000 .
b10000000 3
0+
#185000
1$
0"
b10000000 !
b10000000 7
b1 :
b10000000 9
b1 ?
b10000000 >
1+
#190000
b11000000 B
b11000000 A
0+
#195000
1"
1#
0$
b101111111 !
b101111111 7
1+
#200000
b11000000 /
b11000000 4
b11000000 .
b11000000 3
0+
#205000
1#
0"
b101111111 !
b101111111 7
b11000000 :
b11000000 9
b11000000 ?
b11000000 >
1+
#210000
b1000000 B
b1000000 A
0+
#215000
1&
0#
b0 !
b0 7
1+
#220000
b1000000 /
b1000000 4
b1000000 .
b1000000 3
0+
#225000
1&
b1000000 :
b1000000 9
b1000000 ?
b1000000 >
1+
#230000
b10100 B
b110010 A
0+
#235000
1&
1+
#240000
b10100 /
b10100 4
b110010 .
b110010 3
0+
#245000
1&
b10100 :
b110010 9
b10100 ?
b110010 >
1+
#250000
b11101100 B
b11001110 A
0+
#255000
1$
b11110 !
b11110 7
0&
1+
#260000
b11101100 /
b11101100 4
b11001110 .
b11001110 3
0+
#265000
1$
b11110 !
b11110 7
b11101100 :
b11001110 9
b11101100 ?
b11001110 >
1+
#270000
0)
0+
